{
	"animations": [
		{
			"offsets": [
				190,
				0
			],
			"loop": true,
			"fps": 24,
			"anim": "singLEFT",
			"indices": [],
			"name": "left instance 1"
		},
		{
			"offsets": [
				14,
				0
			],
			"loop": true,
			"fps": 24,
			"anim": "singDOWN",
			"indices": [],
			"name": "down instance 1"
		},
		{
			"offsets": [
				11,
				0
			],
			"loop": true,
			"fps": 24,
			"anim": "idle",
			"indices": [],
			"name": "idle instance 1"
		},
		{
			"offsets": [
				115,
				192
			],
			"loop": true,
			"fps": 24,
			"anim": "singUP",
			"indices": [],
			"name": "up instance 1"
		},
		{
			"offsets": [
				-100,
				-10
			],
			"loop": true,
			"fps": 24,
			"anim": "singRIGHT",
			"indices": [],
			"name": "right instance 1"
		}
	],
	"no_antialiasing": true,
	"image": "characters/phase 2 trauma bob",
	"position": [
		150,
		230
	],
	"healthicon": "traumabob",
	"flip_x": false,
	"healthbar_colors": [
		137,
		99,
		101
	],
	"camera_position": [
		-20,
		10
	],
	"sing_duration": 4,
	"scale": 1.1
}